mfd_win_registry/__init__.py
mfd_win_registry/base.py
mfd_win_registry/constants.py
mfd_win_registry/exceptions.py
mfd_win_registry-1.17.0.dist-info/licenses/AUTHORS.md
mfd_win_registry-1.17.0.dist-info/licenses/LICENSE.md
mfd_win_registry-1.17.0.dist-info/METADATA
mfd_win_registry-1.17.0.dist-info/WHEEL
mfd_win_registry-1.17.0.dist-info/top_level.txt
mfd_win_registry-1.17.0.dist-info/RECORD
