Metadata-Version: 2.4
Name: mfd-win-registry
Version: 1.17.0
Summary: Module for managing Windows registry keys and values.
Project-URL: Homepage, https://github.com/intel/mfd
Project-URL: Repository, https://github.com/intel/mfd-win-registry
Project-URL: Issues, https://github.com/intel/mfd-win-registry/issues
Project-URL: Changelog, https://github.com/intel/mfd-win-registry/blob/main/CHANGELOG.md
Requires-Python: <3.14,>=3.10
License-File: LICENSE.md
License-File: AUTHORS.md
Requires-Dist: mfd-common-libs>=1.11.0
Requires-Dist: mfd-typing>=1.23.0
Requires-Dist: mfd-connect>=7.12.0
Dynamic: license-file
